{
  "schemaVersion": 1,
  "scenarios": [
    {
      "id": "group-policy-processing-errors",
      "name": "Group Policy processing errors",
      "purpose": "Group Policy processing failures from the Operational log plus classic System-log errors (1058, 1085).",
      "group": "UpdatesAndPolicy",
      "channels": [ "Microsoft-Windows-GroupPolicy/Operational", "System" ],
      "requiresAdmin": false,
      "activatesTimeline": true,
      "timelineDimension": "Log",
      "priority": 0,
      "order": 0,
      "version": 1,
      "filters": [
        {
          "comparison": { "property": "LogName", "value": "Microsoft-Windows-GroupPolicy/Operational" },
          "predicates": [
            { "comparison": { "property": "Level", "matchMode": "Many", "values": [ "Error", "Warning" ] } }
          ]
        },
        {
          "comparison": { "property": "LogName", "value": "System" },
          "predicates": [
            { "joinWithAny": false, "comparison": { "property": "Source", "value": "Microsoft-Windows-GroupPolicy" } },
            { "joinWithAny": false, "comparison": { "property": "Id", "matchMode": "Many", "values": [ "1058", "1085" ] } }
          ]
        }
      ]
    },
    {
      "id": "windows-update-diagnostics",
      "name": "Windows Update outcome",
      "purpose": "Windows Update client outcomes, color-coded: successful install (WindowsUpdateClient 19), warnings, and errors.",
      "group": "UpdatesAndPolicy",
      "channels": [ "System" ],
      "requiresAdmin": false,
      "activatesTimeline": true,
      "timelineDimension": "EventId",
      "priority": 0,
      "order": 1,
      "version": 1,
      "filters": [
        {
          "color": "LightGreen",
          "comparison": { "property": "Source", "value": "Microsoft-Windows-WindowsUpdateClient" },
          "predicates": [
            { "comparison": { "property": "Id", "value": "19" } }
          ]
        },
        {
          "color": "LightYellow",
          "comparison": { "property": "Source", "value": "Microsoft-Windows-WindowsUpdateClient" },
          "predicates": [
            { "comparison": { "property": "Level", "value": "Warning" } }
          ]
        },
        {
          "color": "LightRed",
          "comparison": { "property": "Source", "value": "Microsoft-Windows-WindowsUpdateClient" },
          "predicates": [
            { "comparison": { "property": "Level", "value": "Error" } }
          ]
        }
      ]
    },
    {
      "id": "windows-setup-servicing-errors",
      "name": "Windows setup & servicing outcomes",
      "purpose": "Component servicing outcomes on the Setup log: failed (Servicing 3), reboot-required (4, 13), and succeeded (2, 9). Servicing events are logged at Information level, so this keys on the event id, not severity.",
      "group": "UpdatesAndPolicy",
      "channels": [ "Setup" ],
      "requiresAdmin": false,
      "activatesTimeline": true,
      "timelineDimension": "EventId",
      "priority": 1,
      "order": 2,
      "version": 1,
      "filters": [
        {
          "color": "LightRed",
          "comparison": { "property": "Source", "value": "Microsoft-Windows-Servicing" },
          "predicates": [
            { "comparison": { "property": "Id", "value": "3" } }
          ]
        },
        {
          "color": "LightYellow",
          "comparison": { "property": "Source", "value": "Microsoft-Windows-Servicing" },
          "predicates": [
            { "comparison": { "property": "Id", "matchMode": "Many", "values": [ "4", "13" ] } }
          ]
        },
        {
          "color": "LightGreen",
          "comparison": { "property": "Source", "value": "Microsoft-Windows-Servicing" },
          "predicates": [
            { "comparison": { "property": "Id", "matchMode": "Many", "values": [ "2", "9" ] } }
          ]
        }
      ]
    },
    {
      "id": "update-reboot-crash-correlation",
      "name": "Update reboot & crash correlation",
      "purpose": "Update install-to-reboot correlation on the System log: install started / succeeded (WindowsUpdateClient 43, 19), reboot initiated (User32 1074), clean vs unexpected shutdown (6006, 6008), boot (6005), and kernel power / bugcheck (41).",
      "group": "UpdatesAndPolicy",
      "channels": [ "System" ],
      "requiresAdmin": false,
      "activatesTimeline": true,
      "timelineDimension": "EventId",
      "priority": 0,
      "order": 3,
      "version": 1,
      "filters": [
        {
          "color": "LightRed",
          "comparison": { "property": "Source", "value": "EventLog" },
          "predicates": [
            { "comparison": { "property": "Id", "value": "6008" } }
          ]
        },
        {
          "color": "LightRed",
          "comparison": { "property": "Source", "value": "Microsoft-Windows-Kernel-Power" },
          "predicates": [
            { "comparison": { "property": "Id", "value": "41" } }
          ]
        },
        {
          "color": "LightOrange",
          "comparison": { "property": "Source", "value": "User32" },
          "predicates": [
            { "comparison": { "property": "Id", "value": "1074" } }
          ]
        },
        {
          "color": "LightYellow",
          "comparison": { "property": "Source", "value": "EventLog" },
          "predicates": [
            { "comparison": { "property": "Id", "value": "6006" } }
          ]
        },
        {
          "color": "LightGreen",
          "comparison": { "property": "Source", "value": "EventLog" },
          "predicates": [
            { "comparison": { "property": "Id", "value": "6005" } }
          ]
        },
        {
          "color": "LightGreen",
          "comparison": { "property": "Source", "value": "Microsoft-Windows-WindowsUpdateClient" },
          "predicates": [
            { "comparison": { "property": "Id", "value": "19" } }
          ]
        },
        {
          "color": "LightTeal",
          "comparison": { "property": "Source", "value": "Microsoft-Windows-WindowsUpdateClient" },
          "predicates": [
            { "comparison": { "property": "Id", "value": "43" } }
          ]
        }
      ]
    },
    {
      "id": "time-synchronization-failures",
      "name": "Time synchronization failures",
      "purpose": "Windows Time service synchronization problems (Time-Service / W32Time 29, 36, 50, 129, 131).",
      "group": "UpdatesAndPolicy",
      "channels": [ "System" ],
      "optionalChannels": [ "Microsoft-Windows-Time-Service/Operational" ],
      "requiresAdmin": false,
      "activatesTimeline": true,
      "timelineDimension": "EventId",
      "priority": 1,
      "order": 3,
      "version": 1,
      "filters": [
        {
          "comparison": { "property": "Source", "matchMode": "Many", "values": [ "Microsoft-Windows-Time-Service", "W32Time" ] },
          "predicates": [
            { "comparison": { "property": "Id", "matchMode": "Many", "values": [ "29", "36", "50", "129", "131" ] } }
          ]
        }
      ]
    },
    {
      "id": "app-compatibility-issues",
      "name": "App compatibility issues",
      "purpose": "Program Compatibility Assistant errors and warnings for apps that misbehave on this Windows build.",
      "group": "UpdatesAndPolicy",
      "channels": [ "Microsoft-Windows-Application-Experience/Program-Compatibility-Assistant" ],
      "requiresAdmin": false,
      "priority": 1,
      "order": 4,
      "version": 1,
      "filters": [
        {
          "comparison": { "property": "Level", "matchMode": "Many", "values": [ "Error", "Warning" ] }
        }
      ]
    },
    {
      "id": "certificate-lifecycle-events",
      "name": "Certificate lifecycle events",
      "purpose": "Certificate enrollment and renewal errors and warnings on this machine.",
      "group": "UpdatesAndPolicy",
      "channels": [ "Microsoft-Windows-CertificateServicesClient-Lifecycle-System/Operational" ],
      "requiresAdmin": false,
      "priority": 1,
      "order": 5,
      "version": 1,
      "filters": [
        {
          "comparison": { "property": "Level", "matchMode": "Many", "values": [ "Error", "Warning" ] }
        }
      ]
    }
  ]
}
